CHANGES
LICENSE
MANIFEST.in
README.MAINTAINER
README.rst
setup.cfg
setup.py
doc/Makefile
doc/conf.py
doc/index.rst
doc/_static/.placeholder
doc/_templates/.placeholder
sphinxcontrib/__init__.py
sphinxcontrib/mscgen.py
sphinxcontrib_mscgen.egg-info/PKG-INFO
sphinxcontrib_mscgen.egg-info/SOURCES.txt
sphinxcontrib_mscgen.egg-info/dependency_links.txt
sphinxcontrib_mscgen.egg-info/namespace_packages.txt
sphinxcontrib_mscgen.egg-info/not-zip-safe
sphinxcontrib_mscgen.egg-info/requires.txt
sphinxcontrib_mscgen.egg-info/top_level.txt