Metadata-Version: 1.1
Name: sphinxcontrib-mscgen
Version: 0.5
Summary: mscgen Sphinx extension
Home-page: http://packages.python.org/sphinxcontrib-mscgen/
Author: Leandro Lucarella
Author-email: llucax@gmail.com
License: BOLA
Download-URL: http://pypi.python.org/pypi/sphinxcontrib-mscgen
Platform: any
Classifier: Development Status :: 4 - Beta
Classifier: Environment :: Console
Classifier: Environment :: Web Environment
Classifier: Intended Audience :: Developers
Classifier: License :: Public Domain
Classifier: Operating System :: OS Independent
Classifier: Programming Language :: Python
Classifier: Topic :: Documentation
Classifier: Topic :: Utilities
